borneo/__init__.py
borneo/auth.py
borneo/client.py
borneo/common.py
borneo/config.py
borneo/driver.py
borneo/exception.py
borneo/http.py
borneo/nson.py
borneo/nson_protocol.py
borneo/operations.py
borneo/query.py
borneo/serde.py
borneo/serdeutil.py
borneo/stats.py
borneo/version.py
borneo/iam/__init__.py
borneo/iam/iam.py
borneo/kv/__init__.py
borneo/kv/exception.py
borneo/kv/kv.py
borneo-5.4.2.dist-info/LICENSE.txt
borneo-5.4.2.dist-info/METADATA
borneo-5.4.2.dist-info/WHEEL
borneo-5.4.2.dist-info/top_level.txt
borneo-5.4.2.dist-info/RECORD
