Metadata-Version: 2.1
Name: borneo
Version: 5.4.2
Summary: Oracle NoSQL Database Python SDK
Home-page: https://nosql-python-sdk.readthedocs.io/en/stable/index.html
Author: Oracle
Author-email: george.feinberg@oracle.com
License: Universal Permissive License 1.0
Keywords: database,nosql,cloud,development
Classifier: Development Status :: 5 - Production/Stable
Classifier: Intended Audience :: Developers
Classifier: Topic :: Database :: Front-Ends
Classifier: License :: OSI Approved :: Universal Permissive License (UPL)
Classifier: Programming Language :: Python :: 3.5
Classifier: Programming Language :: Python :: 3.6
Classifier: Programming Language :: Python :: 3.7
Classifier: Programming Language :: Python :: 3.8
Classifier: Programming Language :: Python :: 3.9
Classifier: Programming Language :: Python :: 3.10
Classifier: Programming Language :: Python :: 3.11
License-File: LICENSE.txt
Requires-Dist: python-dateutil (>=2.7.0)
Requires-Dist: requests (>=2.12.0)
